aiomonetacleint/__init__.py
aiomonetacleint/client.py
aiomonetacleint/conf.py
aiomonetacleint/decoders.py
aiomonetacleint/models.py
aiomonetaclient-0.0.7.dist-info/LICENSE
aiomonetaclient-0.0.7.dist-info/METADATA
aiomonetaclient-0.0.7.dist-info/WHEEL
aiomonetaclient-0.0.7.dist-info/top_level.txt
aiomonetaclient-0.0.7.dist-info/RECORD
