Metadata-Version: 2.1
Name: aiomonetaclient
Version: 0.0.7
Summary: Aio cleint for moneta merchant api
Home-page: https://github.com/Thaumaturge/aiomonetaclient
Author: Artem Ziborov
Author-email: artimydin@gmail.com
License: UNKNOWN
Project-URL: Bug Tracker, https://github.com/Thaumaturge/aiomonetaclient/issues
Platform: UNKNOWN
Classifier: Programming Language :: Python :: 3
Classifier: License :: OSI Approved :: MIT License
Classifier: Operating System :: OS Independent
Requires-Python: >=3.8.2
License-File: LICENSE
Requires-Dist: aiohttp (==3.7.4)
Requires-Dist: simplejson
